gwtm_api/__init__.py
gwtm_api/alert.py
gwtm_api/candidate.py
gwtm_api/event_tools.py
gwtm_api/instrument.py
gwtm_api/pointing.py
gwtm_api/core/__init__.py
gwtm_api/core/apimodels.py
gwtm_api/core/baseapi.py
gwtm_api/core/tmcache.py
gwtm_api/core/util.py
gwtm_api-0.1.6.dist-info/METADATA
gwtm_api-0.1.6.dist-info/WHEEL
gwtm_api-0.1.6.dist-info/licenses/LICENSE
gwtm_api-0.1.6.dist-info/RECORD
