Metadata-Version: 2.4
Name: gwtm_api
Version: 0.1.6
Summary: A python API wrapper for the Gravitational Wave Treasure Map
Project-URL: Homepage, https://github.com/TheTreasureMap/gwtm_api
Project-URL: Bug Tracker, https://github.com/TheTreasureMap/gwtm_api/issues
Author-email: Samuel Wyatt <samuel.d.wyatt@nasa.gov>
License-File: LICENSE
Classifier: License :: OSI Approved :: MIT License
Classifier: Operating System :: OS Independent
Classifier: Programming Language :: Python :: 3
Requires-Python: <3.12
Requires-Dist: astropy
Requires-Dist: healpy
Requires-Dist: ligo-skymap
Requires-Dist: matplotlib
Requires-Dist: pandas
Requires-Dist: requests
